<Properties StartupConfiguration="{1F100DC9-48F0-4C07-9B61-A2673A77FAEF}|Default">
  <MonoDevelop.Ide.Workbench ActiveDocument="ExtAppraisalApp Status">
    <Files>
      <File FileName="AppraisalApp/Controllers/LoginViewController.cs" Line="91" Column="18" />
      <File FileName="AppraisalApp/Controllers/DetailViewController.cs" Line="29" Column="40" />
      <File FileName="AppraisalApp/Controllers/MasterViewController.cs" Line="22" Column="39" />
      <File FileName="AppraisalApp/Controllers/AfterMarketViewController.cs" Line="219" Column="58" />
      <File FileName="ExtAppraisalApp Status" />
    </Files>
  </MonoDevelop.Ide.Workbench>
  <MonoDevelop.Ide.Workspace ActiveConfiguration="Debug|iPhoneSimulator" />
  <MonoDevelop.Ide.DebuggingService.Breakpoints>
    <BreakpointStore />
  </MonoDevelop.Ide.DebuggingService.Breakpoints>
  <MonoDevelop.Ide.DebuggingService.PinnedWatches>
    <Watch file="../../../AppraisalApp/Controllers/DecodeViewController.cs" line="80" offsetX="784" offsetY="1185" expression="apprrequest.VIN" liveUpdate="True" />
  </MonoDevelop.Ide.DebuggingService.PinnedWatches>
  <MonoDevelop.Ide.ItemProperties.ExtAppraisalApp PreferredExecutionTarget="MonoDevelop.IPhone.IPhoneSimulatorTarget.3B2300C8-F0EC-4B96-B090-BFE6A8AA2D42" />
  <MultiItemStartupConfigurations />
</Properties>